{"version":"2024a","zones":[{"id":"Africa/Abidjan","aliases":["Iceland","Africa/Accra","Africa/Bamako","Africa/Banjul","Africa/Conakry","Africa/Dakar","Africa/Freetown","Africa/Lome","Africa/Nouakchott","Africa/Ouagadougou","Atlantic/Reykjavik","Atlantic/St_Helena","Africa/Timbuktu"]},{"id":"Africa/Algiers","aliases":null},{"id":"Africa/Bissau","aliases":null},{"id":"Africa/Cairo","aliases":["Egypt"]},{"id":"Africa/Casablanca","aliases":null},{"id":"Africa/Ceuta","aliases":null},{"id":"Africa/El_Aaiun","aliases":null},{"id":"Africa/Johannesburg","aliases":["Africa/Maseru","Africa/Mbabane"]},{"id":"Africa/Juba","aliases":null},{"id":"Africa/Khartoum","aliases":null},{"id":"Africa/Lagos","aliases":["Africa/Bangui","Africa/Brazzaville","Africa/Douala","Africa/Kinshasa","Africa/Libreville","Africa/Luanda","Africa/Malabo","Africa/Niamey","Africa/Porto-Novo"]},{"id":"Africa/Maputo","aliases":["Africa/Blantyre","Africa/Bujumbura","Africa/Gaborone","Africa/Harare","Africa/Kigali","Africa/Lubumbashi","Africa/Lusaka"]},{"id":"Africa/Monrovia","aliases":null},{"id":"Africa/Nairobi","aliases":["Africa/Addis_Ababa","Africa/Asmara","Africa/Dar_es_Salaam","Africa/Djibouti","Africa/Kampala","Africa/Mogadishu","Indian/Antananarivo","Indian/Comoro","Indian/Mayotte","Africa/Asmera"]},{"id":"Africa/Ndjamena","aliases":null},{"id":"Africa/Sao_Tome","aliases":null},{"id":"Africa/Tripoli","aliases":["Libya"]},{"id":"Africa/Tunis","aliases":null},{"id":"Africa/Windhoek","aliases":null},{"id":"America/Adak","aliases":["US/Aleutian","America/Atka"]},{"id":"America/Anchorage","aliases":["US/Alaska"]},{"id":"America/Araguaina","aliases":null},{"id":"America/Argentina/Buenos_Aires","aliases":["America/Buenos_Aires"]},{"id":"America/Argentina/Catamarca","aliases":["America/Catamarca","America/Argentina/ComodRivadavia"]},{"id":"America/Argentina/Cordoba","aliases":["America/Cordoba","America/Rosario"]},{"id":"America/Argentina/Jujuy","aliases":["America/Jujuy"]},{"id":"America/Argentina/La_Rioja","aliases":null},{"id":"America/Argentina/Mendoza","aliases":["America/Mendoza"]},{"id":"America/Argentina/Rio_Gallegos","aliases":null},{"id":"America/Argentina/Salta","aliases":null},{"id":"America/Argentina/San_Juan","aliases":null},{"id":"America/Argentina/San_Luis","aliases":null},{"id":"America/Argentina/Tucuman","aliases":null},{"id":"America/Argentina/Ushuaia","aliases":null},{"id":"America/Asuncion","aliases":null},{"id":"America/Bahia","aliases":null},{"id":"America/Bahia_Banderas","aliases":null},{"id":"America/Barbados","aliases":null},{"id":"America/Belem","aliases":null},{"id":"America/Belize","aliases":null},{"id":"America/Boa_Vista","aliases":null},{"id":"America/Bogota","aliases":null},{"id":"America/Boise","aliases":null},{"id":"America/Cambridge_Bay","aliases":null},{"id":"America/Campo_Grande","aliases":null},{"id":"America/Cancun","aliases":null},{"id":"America/Caracas","aliases":null},{"id":"America/Cayenne","aliases":null},{"id":"America/Chicago","aliases":["US/Central"]},{"id":"America/Chihuahua","aliases":null},{"id":"America/Ciudad_Juarez","aliases":null},{"id":"America/Costa_Rica","aliases":null},{"id":"America/Cuiaba","aliases":null},{"id":"America/Danmarkshavn","aliases":null},{"id":"America/Dawson","aliases":null},{"id":"America/Dawson_Creek","aliases":null},{"id":"America/Denver","aliases":["Navajo","US/Mountain","America/Shiprock"]},{"id":"America/Detroit","aliases":["US/Michigan"]},{"id":"America/Edmonton","aliases":["Canada/Mountain","America/Yellowknife"]},{"id":"America/Eirunepe","aliases":null},{"id":"America/El_Salvador","aliases":null},{"id":"America/Fort_Nelson","aliases":null},{"id":"America/Fortaleza","aliases":null},{"id":"America/Glace_Bay","aliases":null},{"id":"America/Goose_Bay","aliases":null},{"id":"America/Grand_Turk","aliases":null},{"id":"America/Guatemala","aliases":null},{"id":"America/Guayaquil","aliases":null},{"id":"America/Guyana","aliases":null},{"id":"America/Halifax","aliases":["Canada/Atlantic"]},{"id":"America/Havana","aliases":["Cuba"]},{"id":"America/Hermosillo","aliases":null},{"id":"America/Indiana/Indianapolis","aliases":["US/East-Indiana","America/Indianapolis","America/Fort_Wayne"]},{"id":"America/Indiana/Knox","aliases":["US/Indiana-Starke","America/Knox_IN"]},{"id":"America/Indiana/Marengo","aliases":null},{"id":"America/Indiana/Petersburg","aliases":null},{"id":"America/Indiana/Tell_City","aliases":null},{"id":"America/Indiana/Vevay","aliases":null},{"id":"America/Indiana/Vincennes","aliases":null},{"id":"America/Indiana/Winamac","aliases":null},{"id":"America/Inuvik","aliases":null},{"id":"America/Iqaluit","aliases":["America/Pangnirtung"]},{"id":"America/Jamaica","aliases":["Jamaica"]},{"id":"America/Juneau","aliases":null},{"id":"America/Kentucky/Louisville","aliases":["America/Louisville"]},{"id":"America/Kentucky/Monticello","aliases":null},{"id":"America/La_Paz","aliases":null},{"id":"America/Lima","aliases":null},{"id":"America/Los_Angeles","aliases":["US/Pacific"]},{"id":"America/Maceio","aliases":null},{"id":"America/Managua","aliases":null},{"id":"America/Manaus","aliases":["Brazil/West"]},{"id":"America/Martinique","aliases":null},{"id":"America/Matamoros","aliases":null},{"id":"America/Mazatlan","aliases":["Mexico/BajaSur"]},{"id":"America/Menominee","aliases":null},{"id":"America/Merida","aliases":null},{"id":"America/Metlakatla","aliases":null},{"id":"America/Mexico_City","aliases":["Mexico/General"]},{"id":"America/Miquelon","aliases":null},{"id":"America/Moncton","aliases":null},{"id":"America/Monterrey","aliases":null},{"id":"America/Montevideo","aliases":null},{"id":"America/New_York","aliases":["US/Eastern"]},{"id":"America/Nome","aliases":null},{"id":"America/Noronha","aliases":["Brazil/DeNoronha"]},{"id":"America/North_Dakota/Beulah","aliases":null},{"id":"America/North_Dakota/Center","aliases":null},{"id":"America/North_Dakota/New_Salem","aliases":null},{"id":"America/Nuuk","aliases":["America/Godthab"]},{"id":"America/Ojinaga","aliases":null},{"id":"America/Panama","aliases":["America/Atikokan","America/Cayman","America/Coral_Harbour"]},{"id":"America/Paramaribo","aliases":null},{"id":"America/Phoenix","aliases":["US/Arizona","America/Creston"]},{"id":"America/Port-au-Prince","aliases":null},{"id":"America/Porto_Velho","aliases":null},{"id":"America/Puerto_Rico","aliases":["America/Virgin","America/Anguilla","America/Antigua","America/Aruba","America/Blanc-Sablon","America/Curacao","America/Dominica","America/Grenada","America/Guadeloupe","America/Kralendijk","America/Lower_Princes","America/Marigot","America/Montserrat","America/Port_of_Spain","America/St_Barthelemy","America/St_Kitts","America/St_Lucia","America/St_Thomas","America/St_Vincent","America/Tortola"]},{"id":"America/Punta_Arenas","aliases":null},{"id":"America/Rankin_Inlet","aliases":null},{"id":"America/Recife","aliases":null},{"id":"America/Regina","aliases":["Canada/Saskatchewan"]},{"id":"America/Resolute","aliases":null},{"id":"America/Rio_Branco","aliases":["Brazil/Acre","America/Porto_Acre"]},{"id":"America/Santarem","aliases":null},{"id":"America/Santiago","aliases":["Chile/Continental"]},{"id":"America/Santo_Domingo","aliases":null},{"id":"America/Sao_Paulo","aliases":["Brazil/East"]},{"id":"America/Scoresbysund","aliases":null},{"id":"America/Sitka","aliases":null},{"id":"America/St_Johns","aliases":["Canada/Newfoundland"]},{"id":"America/Swift_Current","aliases":null},{"id":"America/Tegucigalpa","aliases":null},{"id":"America/Thule","aliases":null},{"id":"America/Tijuana","aliases":["Mexico/BajaNorte","America/Ensenada","America/Santa_Isabel"]},{"id":"America/Toronto","aliases":["Canada/Eastern","America/Nassau","America/Montreal","America/Nipigon","America/Thunder_Bay"]},{"id":"America/Vancouver","aliases":["Canada/Pacific"]},{"id":"America/Whitehorse","aliases":["Canada/Yukon"]},{"id":"America/Winnipeg","aliases":["Canada/Central","America/Rainy_River"]},{"id":"America/Yakutat","aliases":null},{"id":"Antarctica/Casey","aliases":null},{"id":"Antarctica/Davis","aliases":null},{"id":"Antarctica/Macquarie","aliases":null},{"id":"Antarctica/Mawson","aliases":null},{"id":"Antarctica/Palmer","aliases":null},{"id":"Antarctica/Rothera","aliases":null},{"id":"Antarctica/Troll","aliases":null},{"id":"Antarctica/Vostok","aliases":null},{"id":"Asia/Almaty","aliases":null},{"id":"Asia/Amman","aliases":null},{"id":"Asia/Anadyr","aliases":null},{"id":"Asia/Aqtau","aliases":null},{"id":"Asia/Aqtobe","aliases":null},{"id":"Asia/Ashgabat","aliases":["Asia/Ashkhabad"]},{"id":"Asia/Atyrau","aliases":null},{"id":"Asia/Baghdad","aliases":null},{"id":"Asia/Baku","aliases":null},{"id":"Asia/Bangkok","aliases":["Asia/Phnom_Penh","Asia/Vientiane","Indian/Christmas"]},{"id":"Asia/Barnaul","aliases":null},{"id":"Asia/Beirut","aliases":null},{"id":"Asia/Bishkek","aliases":null},{"id":"Asia/Chita","aliases":null},{"id":"Asia/Choibalsan","aliases":null},{"id":"Asia/Colombo","aliases":null},{"id":"Asia/Damascus","aliases":null},{"id":"Asia/Dhaka","aliases":["Asia/Dacca"]},{"id":"Asia/Dili","aliases":null},{"id":"Asia/Dubai","aliases":["Asia/Muscat","Indian/Mahe","Indian/Reunion"]},{"id":"Asia/Dushanbe","aliases":null},{"id":"Asia/Famagusta","aliases":null},{"id":"Asia/Gaza","aliases":null},{"id":"Asia/Hebron","aliases":null},{"id":"Asia/Ho_Chi_Minh","aliases":["Asia/Saigon"]},{"id":"Asia/Hong_Kong","aliases":["Hongkong"]},{"id":"Asia/Hovd","aliases":null},{"id":"Asia/Irkutsk","aliases":null},{"id":"Asia/Jakarta","aliases":null},{"id":"Asia/Jayapura","aliases":null},{"id":"Asia/Jerusalem","aliases":["Israel","Asia/Tel_Aviv"]},{"id":"Asia/Kabul","aliases":null},{"id":"Asia/Kamchatka","aliases":null},{"id":"Asia/Karachi","aliases":null},{"id":"Asia/Kathmandu","aliases":["Asia/Katmandu"]},{"id":"Asia/Khandyga","aliases":null},{"id":"Asia/Kolkata","aliases":["Asia/Calcutta"]},{"id":"Asia/Krasnoyarsk","aliases":null},{"id":"Asia/Kuching","aliases":["Asia/Brunei"]},{"id":"Asia/Macau","aliases":["Asia/Macao"]},{"id":"Asia/Magadan","aliases":null},{"id":"Asia/Makassar","aliases":["Asia/Ujung_Pandang"]},{"id":"Asia/Manila","aliases":null},{"id":"Asia/Nicosia","aliases":["Europe/Nicosia"]},{"id":"Asia/Novokuznetsk","aliases":null},{"id":"Asia/Novosibirsk","aliases":null},{"id":"Asia/Omsk","aliases":null},{"id":"Asia/Oral","aliases":null},{"id":"Asia/Pontianak","aliases":null},{"id":"Asia/Pyongyang","aliases":null},{"id":"Asia/Qatar","aliases":["Asia/Bahrain"]},{"id":"Asia/Qostanay","aliases":null},{"id":"Asia/Qyzylorda","aliases":null},{"id":"Asia/Riyadh","aliases":["Antarctica/Syowa","Asia/Aden","Asia/Kuwait"]},{"id":"Asia/Sakhalin","aliases":null},{"id":"Asia/Samarkand","aliases":null},{"id":"Asia/Seoul","aliases":["ROK"]},{"id":"Asia/Shanghai","aliases":["PRC","Asia/Chongqing","Asia/Harbin","Asia/Chungking"]},{"id":"Asia/Singapore","aliases":["Singapore","Asia/Kuala_Lumpur"]},{"id":"Asia/Srednekolymsk","aliases":null},{"id":"Asia/Taipei","aliases":["ROC"]},{"id":"Asia/Tashkent","aliases":null},{"id":"Asia/Tbilisi","aliases":null},{"id":"Asia/Tehran","aliases":["Iran"]},{"id":"Asia/Thimphu","aliases":["Asia/Thimbu"]},{"id":"Asia/Tokyo","aliases":["Japan"]},{"id":"Asia/Tomsk","aliases":null},{"id":"Asia/Ulaanbaatar","aliases":["Asia/Ulan_Bator"]},{"id":"Asia/Urumqi","aliases":["Asia/Kashgar"]},{"id":"Asia/Ust-Nera","aliases":null},{"id":"Asia/Vladivostok","aliases":null},{"id":"Asia/Yakutsk","aliases":null},{"id":"Asia/Yangon","aliases":["Indian/Cocos","Asia/Rangoon"]},{"id":"Asia/Yekaterinburg","aliases":null},{"id":"Asia/Yerevan","aliases":null},{"id":"Atlantic/Azores","aliases":null},{"id":"Atlantic/Bermuda","aliases":null},{"id":"Atlantic/Canary","aliases":null},{"id":"Atlantic/Cape_Verde","aliases":null},{"id":"Atlantic/Faroe","aliases":["Atlantic/Faeroe"]},{"id":"Atlantic/Madeira","aliases":null},{"id":"Atlantic/South_Georgia","aliases":null},{"id":"Atlantic/Stanley","aliases":null},{"id":"Australia/Adelaide","aliases":["Australia/South"]},{"id":"Australia/Brisbane","aliases":["Australia/Queensland"]},{"id":"Australia/Broken_Hill","aliases":["Australia/Yancowinna"]},{"id":"Australia/Darwin","aliases":["Australia/North"]},{"id":"Australia/Eucla","aliases":null},{"id":"Australia/Hobart","aliases":["Australia/Tasmania","Australia/Currie"]},{"id":"Australia/Lindeman","aliases":null},{"id":"Australia/Lord_Howe","aliases":["Australia/LHI"]},{"id":"Australia/Melbourne","aliases":["Australia/Victoria"]},{"id":"Australia/Perth","aliases":["Australia/West"]},{"id":"Australia/Sydney","aliases":["Australia/ACT","Australia/NSW","Australia/Canberra"]},{"id":"CET","aliases":null},{"id":"CST6CDT","aliases":null},{"id":"EET","aliases":null},{"id":"EST","aliases":null},{"id":"EST5EDT","aliases":null},{"id":"Etc/GMT","aliases":["GMT","Etc/GMT+0","Etc/GMT-0","Etc/GMT0","Etc/Greenwich","GMT+0","GMT-0","GMT0","Greenwich"]},{"id":"Etc/GMT+1","aliases":null},{"id":"Etc/GMT+10","aliases":null},{"id":"Etc/GMT+11","aliases":null},{"id":"Etc/GMT+12","aliases":null},{"id":"Etc/GMT+2","aliases":null},{"id":"Etc/GMT+3","aliases":null},{"id":"Etc/GMT+4","aliases":null},{"id":"Etc/GMT+5","aliases":null},{"id":"Etc/GMT+6","aliases":null},{"id":"Etc/GMT+7","aliases":null},{"id":"Etc/GMT+8","aliases":null},{"id":"Etc/GMT+9","aliases":null},{"id":"Etc/GMT-1","aliases":null},{"id":"Etc/GMT-10","aliases":null},{"id":"Etc/GMT-11","aliases":null},{"id":"Etc/GMT-12","aliases":null},{"id":"Etc/GMT-13","aliases":null},{"id":"Etc/GMT-14","aliases":null},{"id":"Etc/GMT-2","aliases":null},{"id":"Etc/GMT-3","aliases":null},{"id":"Etc/GMT-4","aliases":null},{"id":"Etc/GMT-5","aliases":null},{"id":"Etc/GMT-6","aliases":null},{"id":"Etc/GMT-7","aliases":null},{"id":"Etc/GMT-8","aliases":null},{"id":"Etc/GMT-9","aliases":null},{"id":"Etc/UTC","aliases":["Etc/UCT","Etc/Universal","Etc/Zulu","UCT","UTC","Universal","Zulu"]},{"id":"Europe/Andorra","aliases":null},{"id":"Europe/Astrakhan","aliases":null},{"id":"Europe/Athens","aliases":null},{"id":"Europe/Belgrade","aliases":["Europe/Ljubljana","Europe/Podgorica","Europe/Sarajevo","Europe/Skopje","Europe/Zagreb"]},{"id":"Europe/Berlin","aliases":["Arctic/Longyearbyen","Europe/Copenhagen","Europe/Oslo","Europe/Stockholm","Atlantic/Jan_Mayen"]},{"id":"Europe/Brussels","aliases":["Europe/Amsterdam","Europe/Luxembourg"]},{"id":"Europe/Bucharest","aliases":null},{"id":"Europe/Budapest","aliases":null},{"id":"Europe/Chisinau","aliases":["Europe/Tiraspol"]},{"id":"Europe/Dublin","aliases":["Eire"]},{"id":"Europe/Gibraltar","aliases":null},{"id":"Europe/Helsinki","aliases":["Europe/Mariehamn"]},{"id":"Europe/Istanbul","aliases":["Turkey","Asia/Istanbul"]},{"id":"Europe/Kaliningrad","aliases":null},{"id":"Europe/Kirov","aliases":null},{"id":"Europe/Kyiv","aliases":["Europe/Uzhgorod","Europe/Zaporozhye","Europe/Kiev"]},{"id":"Europe/Lisbon","aliases":["Portugal"]},{"id":"Europe/London","aliases":["GB","GB-Eire","Europe/Guernsey","Europe/Isle_of_Man","Europe/Jersey","Europe/Belfast"]},{"id":"Europe/Madrid","aliases":null},{"id":"Europe/Malta","aliases":null},{"id":"Europe/Minsk","aliases":null},{"id":"Europe/Moscow","aliases":["W-SU"]},{"id":"Europe/Paris","aliases":["Europe/Monaco"]},{"id":"Europe/Prague","aliases":["Europe/Bratislava"]},{"id":"Europe/Riga","aliases":null},{"id":"Europe/Rome","aliases":["Europe/San_Marino","Europe/Vatican"]},{"id":"Europe/Samara","aliases":null},{"id":"Europe/Saratov","aliases":null},{"id":"Europe/Simferopol","aliases":null},{"id":"Europe/Sofia","aliases":null},{"id":"Europe/Tallinn","aliases":null},{"id":"Europe/Tirane","aliases":null},{"id":"Europe/Ulyanovsk","aliases":null},{"id":"Europe/Vienna","aliases":null},{"id":"Europe/Vilnius","aliases":null},{"id":"Europe/Volgograd","aliases":null},{"id":"Europe/Warsaw","aliases":["Poland"]},{"id":"Europe/Zurich","aliases":["Europe/Busingen","Europe/Vaduz"]},{"id":"Factory","aliases":null},{"id":"HST","aliases":null},{"id":"Indian/Chagos","aliases":null},{"id":"Indian/Maldives","aliases":["Indian/Kerguelen"]},{"id":"Indian/Mauritius","aliases":null},{"id":"MET","aliases":null},{"id":"MST","aliases":null},{"id":"MST7MDT","aliases":null},{"id":"PST8PDT","aliases":null},{"id":"Pacific/Apia","aliases":null},{"id":"Pacific/Auckland","aliases":["NZ","Antarctica/McMurdo","Antarctica/South_Pole"]},{"id":"Pacific/Bougainville","aliases":null},{"id":"Pacific/Chatham","aliases":["NZ-CHAT"]},{"id":"Pacific/Easter","aliases":["Chile/EasterIsland"]},{"id":"Pacific/Efate","aliases":null},{"id":"Pacific/Fakaofo","aliases":null},{"id":"Pacific/Fiji","aliases":null},{"id":"Pacific/Galapagos","aliases":null},{"id":"Pacific/Gambier","aliases":null},{"id":"Pacific/Guadalcanal","aliases":["Pacific/Pohnpei","Pacific/Ponape"]},{"id":"Pacific/Guam","aliases":["Pacific/Saipan"]},{"id":"Pacific/Honolulu","aliases":["US/Hawaii","Pacific/Johnston"]},{"id":"Pacific/Kanton","aliases":["Pacific/Enderbury"]},{"id":"Pacific/Kiritimati","aliases":null},{"id":"Pacific/Kosrae","aliases":null},{"id":"Pacific/Kwajalein","aliases":["Kwajalein"]},{"id":"Pacific/Marquesas","aliases":null},{"id":"Pacific/Nauru","aliases":null},{"id":"Pacific/Niue","aliases":null},{"id":"Pacific/Norfolk","aliases":null},{"id":"Pacific/Noumea","aliases":null},{"id":"Pacific/Pago_Pago","aliases":["US/Samoa","Pacific/Samoa","Pacific/Midway"]},{"id":"Pacific/Palau","aliases":null},{"id":"Pacific/Pitcairn","aliases":null},{"id":"Pacific/Port_Moresby","aliases":["Antarctica/DumontDUrville","Pacific/Chuuk","Pacific/Yap","Pacific/Truk"]},{"id":"Pacific/Rarotonga","aliases":null},{"id":"Pacific/Tahiti","aliases":null},{"id":"Pacific/Tarawa","aliases":["Pacific/Funafuti","Pacific/Majuro","Pacific/Wake","Pacific/Wallis"]},{"id":"Pacific/Tongatapu","aliases":null},{"id":"WET","aliases":null}]}